facet_mcp/__init__.py
facet_mcp/cli.py
facet_mcp/server.py
facet_mcp/config/__init__.py
facet_mcp/config/settings.py
facet_mcp/core/__init__.py
facet_mcp/core/facets.py
facet_mcp/core/validator.py
facet_mcp/protocol/__init__.py
facet_mcp/protocol/messages.py
facet_mcp/protocol/transport.py
facet_mcp/tools/__init__.py
facet_mcp/tools/facets.py
facet_mcp_server-0.1.0.dist-info/licenses/LICENSE
facet_mcp_server-0.1.0.dist-info/METADATA
facet_mcp_server-0.1.0.dist-info/WHEEL
facet_mcp_server-0.1.0.dist-info/entry_points.txt
facet_mcp_server-0.1.0.dist-info/top_level.txt
facet_mcp_server-0.1.0.dist-info/RECORD
