Metadata-Version: 2.4
Name: facet-mcp-server
Version: 0.1.0
Summary: FACET MCP Server - Agent-First AI Tooling
Home-page: https://github.com/rokoss21/FACET
Author: Emil Rokossovskiy
Author-email: Emil Rokossovskiy <ecsiar@gmail.com>
Maintainer-email: Emil Rokossovskiy <ecsiar@gmail.com>
License: MIT
Project-URL: Homepage, https://github.com/rokoss21/FACET_mcp
Project-URL: Documentation, https://facet-mcp-server.readthedocs.io/
Project-URL: Repository, https://github.com/rokoss21/FACET_mcp
Project-URL: Issues, https://github.com/rokoss21/FACET_mcp/issues
Project-URL: Changelog, https://github.com/rokoss21/FACET_mcp/blob/main/CHANGELOG.md
Keywords: ai,agents,mcp,facet,text-processing,simd,websocket
Classifier: Development Status :: 4 - Beta
Classifier: Intended Audience :: Developers
Classifier: Intended Audience :: Science/Research
Classifier: License :: OSI Approved :: MIT License
Classifier: Operating System :: OS Independent
Classifier: Programming Language :: Python :: 3
Classifier: Programming Language :: Python :: 3.9
Classifier: Programming Language :: Python :: 3.10
Classifier: Programming Language :: Python :: 3.11
Classifier: Programming Language :: Python :: 3.12
Classifier: Topic :: Scientific/Engineering :: Artificial Intelligence
Classifier: Topic :: Software Development :: Libraries
Classifier: Topic :: Text Processing
Requires-Python: >=3.9
License-File: LICENSE
Requires-Dist: websockets>=12.0
Requires-Dist: jsonschema>=4.0
Requires-Dist: uvloop>=0.17.0; sys_platform != "win32"
Requires-Dist: numba>=0.56.0
Requires-Dist: numpy>=1.21.0
Provides-Extra: dev
Requires-Dist: pytest>=7.0; extra == "dev"
Requires-Dist: pytest-asyncio; extra == "dev"
Requires-Dist: pytest-cov; extra == "dev"
Requires-Dist: black; extra == "dev"
Requires-Dist: isort; extra == "dev"
Requires-Dist: flake8; extra == "dev"
Requires-Dist: mypy; extra == "dev"
Requires-Dist: pre-commit; extra == "dev"
Provides-Extra: docs
Requires-Dist: sphinx; extra == "docs"
Requires-Dist: sphinx-rtd-theme; extra == "docs"
Requires-Dist: myst-parser; extra == "docs"
Provides-Extra: all
Requires-Dist: facet-mcp-server[dev,docs]; extra == "all"
Dynamic: author
Dynamic: home-page
Dynamic: license-file
Dynamic: requires-python
